setup.py
django_zonecms.egg-info/PKG-INFO
django_zonecms.egg-info/SOURCES.txt
django_zonecms.egg-info/dependency_links.txt
django_zonecms.egg-info/requires.txt
django_zonecms.egg-info/top_level.txt
djzone_cms/__init__.py
djzone_cms/admin.py
djzone_cms/models.py
djzone_cms/tests.py
djzone_cms/views.py
djzone_cms/templatetags/__init__.py
djzone_cms/templatetags/project_tags.py