Metadata-Version: 1.0
Name: django-zonecms
Version: 0.1.0
Summary: Minimal cms for single page websites with dynamic content.
Home-page: http://github.com/argaen/django_zonecms
Author: argaen
Author-email: manu.mirandad@gmail.com
License: UNKNOWN
Keywords: django,cms,dynamic,single page
Platform: UNKNOWN
